fails_components_jupyter_filesystem_extension/__init__.py
fails_components_jupyter_filesystem_extension/labextension/_version.py
fails_components_jupyter_filesystem_extension/labextension/package.json
fails_components_jupyter_filesystem_extension/labextension/schemas/@fails-components/jupyter-filesystem-extension/package.json.orig
fails_components_jupyter_filesystem_extension/labextension/static/0.b5aa500e97f6f2cbcab1.js
fails_components_jupyter_filesystem_extension/labextension/static/292.347f8a2557c0ace8cba6.js
fails_components_jupyter_filesystem_extension/labextension/static/696.ff9b9d99d5fa51f3fabe.js
fails_components_jupyter_filesystem_extension/labextension/static/remoteEntry.bc97cfc88fd198e89cc0.js
fails_components_jupyter_filesystem_extension/labextension/static/style.js
fails_components_jupyter_filesystem_extension/labextension/static/third-party-licenses.json
fails_components_jupyter_filesystem_extension-0.0.5.data/data/share/jupyter/labextensions/@fails-components/jupyter-filesystem-extension/_version.py
fails_components_jupyter_filesystem_extension-0.0.5.data/data/share/jupyter/labextensions/@fails-components/jupyter-filesystem-extension/package.json
fails_components_jupyter_filesystem_extension-0.0.5.data/data/share/jupyter/labextensions/@fails-components/jupyter-filesystem-extension/schemas/@fails-components/jupyter-filesystem-extension/package.json.orig
fails_components_jupyter_filesystem_extension-0.0.5.data/data/share/jupyter/labextensions/@fails-components/jupyter-filesystem-extension/static/0.b5aa500e97f6f2cbcab1.js
fails_components_jupyter_filesystem_extension-0.0.5.data/data/share/jupyter/labextensions/@fails-components/jupyter-filesystem-extension/static/292.347f8a2557c0ace8cba6.js
fails_components_jupyter_filesystem_extension-0.0.5.data/data/share/jupyter/labextensions/@fails-components/jupyter-filesystem-extension/static/696.ff9b9d99d5fa51f3fabe.js
fails_components_jupyter_filesystem_extension-0.0.5.dist-info/METADATA
fails_components_jupyter_filesystem_extension-0.0.5.dist-info/WHEEL
fails_components_jupyter_filesystem_extension-0.0.5.dist-info/licenses/LICENSE
fails_components_jupyter_filesystem_extension-0.0.5.dist-info/RECORD
