Metadata-Version: 2.4
Name: fails-components-jupyter-filesystem-extension
Version: 0.0.5
Dynamic: Keywords
Summary: A collection of extensions, that redirect's filesystems access to fails and let fails puppeteer Jupyter lite. 
Project-URL: Homepage, https://github.com/fails-components/jupyterfails
Project-URL: Bug Tracker, https://github.com/fails-components/jupyterfails/issues
Project-URL: Repository, https://github.com/fails-components/jupyterfails.git
Author-email: Marten Richter <marten.richter@freenet.de>
License: BSD 3-Clause License
License-File: LICENSE
Classifier: Framework :: Jupyter
Classifier: Framework :: Jupyter :: JupyterLab
Classifier: Framework :: Jupyter :: JupyterLab :: 4
Classifier: Framework :: Jupyter :: JupyterLab :: Extensions
Classifier: Framework :: Jupyter :: JupyterLab :: Extensions :: Prebuilt
Classifier: License :: OSI Approved :: BSD License
Classifier: Programming Language :: Python
Classifier: Programming Language :: Python :: 3
Classifier: Programming Language :: Python :: 3.8
Classifier: Programming Language :: Python :: 3.9
Classifier: Programming Language :: Python :: 3.10
Classifier: Programming Language :: Python :: 3.11
Classifier: Programming Language :: Python :: 3.12
Requires-Python: >=3.8
